sadcompressor-0.1.0.dist-info/METADATA
sadcompressor-0.1.0.dist-info/WHEEL
sadcompressor-0.1.0.dist-info/entry_points.txt
sadcompressor-0.1.0.dist-info/licenses/LICENSE.md
sadcompressor/__init__.py
sadcompressor/frame.py
sadcompressor/container.py
sadcompressor/_version.py
sadcompressor/log.py
sadcompressor/bin/__init__.py
sadcompressor/bin/sadinfo.py
sadcompressor/bin/sadump.py
sadcompressor/bin/sadcopy.py
sadcompressor/streamer.py
sadcompressor/encoder.py
sadcompressor/_rusted.cpython-310-x86_64-linux-gnu.so
sadcompressor-0.1.0.dist-info/RECORD
